llmSHAP/__init__.py
llmSHAP/attribution.py
llmSHAP/data_handler.py
llmSHAP/generation.py
llmSHAP/image.py
llmSHAP/prompt_codec.py
llmSHAP/types.py
llmSHAP/value_functions.py
llmSHAP/attribution_methods/__init__.py
llmSHAP/attribution_methods/attribution_function.py
llmSHAP/attribution_methods/coalition_sampler.py
llmSHAP/attribution_methods/shapley_attribution.py
llmSHAP/llm/__init__.py
llmSHAP/llm/langchain.py
llmSHAP/llm/llm_interface.py
llmSHAP/llm/openai.py
llmshap-1.5.0.dist-info/licenses/LICENSE
llmshap-1.5.0.dist-info/METADATA
llmshap-1.5.0.dist-info/WHEEL
llmshap-1.5.0.dist-info/top_level.txt
llmshap-1.5.0.dist-info/RECORD
