Metadata-Version: 2.4
Name: llmSHAP
Version: 1.5.0
Summary: Multi-threaded Shapley explainability for LLMs: words, sentences, documents, and tools.
Author: Filip Naudot
License-Expression: MIT
Project-URL: Homepage, https://github.com/filipnaudot/llmSHAP
Project-URL: Repository, https://github.com/filipnaudot/llmSHAP
Project-URL: Documentation, https://filipnaudot.github.io/llmSHAP/
Project-URL: Issues, https://github.com/filipnaudot/llmSHAP/issues
Classifier: Development Status :: 3 - Alpha
Classifier: Intended Audience :: Developers
Classifier: Operating System :: OS Independent
Classifier: Programming Language :: Python :: 3
Classifier: Programming Language :: Python :: 3 :: Only
Classifier: Programming Language :: Python :: 3.11
Classifier: Topic :: Scientific/Engineering :: Artificial Intelligence
Requires-Python: >=3.11
License-File: LICENSE
Requires-Dist: tqdm
Requires-Dist: scikit-learn
Provides-Extra: openai
Requires-Dist: openai; extra == "openai"
Requires-Dist: python-dotenv; extra == "openai"
Provides-Extra: embeddings
Requires-Dist: sentence-transformers; extra == "embeddings"
Provides-Extra: dev
Requires-Dist: pytest; extra == "dev"
Requires-Dist: matplotlib; extra == "dev"
Requires-Dist: ipywidgets; extra == "dev"
Requires-Dist: sphinx; extra == "dev"
Requires-Dist: myst-parser; extra == "dev"
Requires-Dist: sphinx-book-theme; extra == "dev"
Requires-Dist: sphinx-design; extra == "dev"
Provides-Extra: full
Requires-Dist: openai; extra == "full"
Requires-Dist: python-dotenv; extra == "full"
Requires-Dist: sentence-transformers; extra == "full"
Requires-Dist: pytest; extra == "full"
Requires-Dist: matplotlib; extra == "full"
Requires-Dist: ipywidgets; extra == "full"
Requires-Dist: sphinx; extra == "full"
Requires-Dist: myst-parser; extra == "full"
Requires-Dist: sphinx-book-theme; extra == "full"
Requires-Dist: sphinx-design; extra == "full"
Dynamic: license-file
